README.md
setup.py
nanoepiseg/__init__.py
nanoepiseg/__main__.py
nanoepiseg/emissions.py
nanoepiseg/hmm.py
nanoepiseg/main_chunked.py
nanoepiseg/main_list_chunks.py
nanoepiseg/math.py
nanoepiseg/postprocessing.py
nanoepiseg/segments_csv_io.py
nanoepiseg.egg-info/PKG-INFO
nanoepiseg.egg-info/SOURCES.txt
nanoepiseg.egg-info/dependency_links.txt
nanoepiseg.egg-info/entry_points.txt
nanoepiseg.egg-info/requires.txt
nanoepiseg.egg-info/top_level.txt