Metadata-Version: 2.1
Name: nanoepiseg
Version: 0.1.0b1
Summary: Methylome segmentation algorithm using a changepoint detection HMM
Home-page: https://github.com/snajder-r/nanoepiseg
Author: Rene Snajder
Author-email: r.snajder@dkfz-heidelberg.de
License: MIT
Platform: UNKNOWN
Classifier: Development Status :: 3 - Alpha
Classifier: Intended Audience :: Science/Research
Classifier: Topic :: Scientific/Engineering :: Bio-Informatics
Classifier: License :: OSI Approved :: MIT License
Classifier: Programming Language :: Python :: 3
Requires-Python: >=3.7
